myosotis_chinese_dictionary/__init__.py
myosotis_chinese_dictionary/dictionary.py
myosotis_chinese_dictionary/dictionaries/bopomofo/dictionary.json
myosotis_chinese_dictionary/dictionaries/bopomofo_first/dictionary.json
myosotis_chinese_dictionary/dictionaries/finals/dictionary.json
myosotis_chinese_dictionary/dictionaries/finals_tone/dictionary.json
myosotis_chinese_dictionary/dictionaries/finals_tone2/dictionary.json
myosotis_chinese_dictionary/dictionaries/finals_tone3/dictionary.json
myosotis_chinese_dictionary/dictionaries/initials/dictionary.json
myosotis_chinese_dictionary/dictionaries/normal/dictionary.json
myosotis_chinese_dictionary/dictionaries/tone/dictionary.json
myosotis_chinese_dictionary/dictionaries/tone2/dictionary.json
myosotis_chinese_dictionary/dictionaries/tone3/dictionary.json
myosotis_chinese_dictionary-0.0.7.dist-info/licenses/LICENSE
myosotis_chinese_dictionary-0.0.7.dist-info/METADATA
myosotis_chinese_dictionary-0.0.7.dist-info/WHEEL
myosotis_chinese_dictionary-0.0.7.dist-info/top_level.txt
myosotis_chinese_dictionary-0.0.7.dist-info/RECORD
